README.md
setup.cfg
setup.py
algolia_places/__init__.py
algolia_places/client.py
algolia_places/hit.py
algolia_places/response.py
algolia_places/struct.py
algolia_places_python.egg-info/PKG-INFO
algolia_places_python.egg-info/SOURCES.txt
algolia_places_python.egg-info/dependency_links.txt
algolia_places_python.egg-info/requires.txt
algolia_places_python.egg-info/top_level.txt
tests/__init__.py
tests/test_client.py
tests/test_hit.py
tests/test_response.py
tests/test_struct.py